soundpython/__init__.py
soundpython/audio.py
soundpython/py.typed
tests/__init__.py
tests/test_audio.py
soundpython-0.1.11.dist-info/METADATA
soundpython-0.1.11.dist-info/WHEEL
soundpython-0.1.11.dist-info/top_level.txt
soundpython-0.1.11.dist-info/RECORD
