Metadata-Version: 2.4
Name: soundpython
Version: 0.1.11
Summary: Simple audio processing library.
Requires-Python: >=3.10
Requires-Dist: numpy>=2.1.0
